pandas_oop/__init__.py
pandas_oop/_decorators.py
pandas_oop/custom_exceptions.py
pandas_oop/fields.py
pandas_oop/models.py
pandas_oop-0.9.6.dist-info/LICENSE
pandas_oop-0.9.6.dist-info/METADATA
pandas_oop-0.9.6.dist-info/WHEEL
pandas_oop-0.9.6.dist-info/top_level.txt
pandas_oop-0.9.6.dist-info/RECORD
