Metadata-Version: 2.1
Name: pandas-oop
Version: 0.9.6
Summary: Pandas dataframes with object oriented programming style
Home-page: https://github.com/MayasMess/pandas-oop
Author: Amayas Messara
Author-email: amayas.messara@gmail.com
License: UNKNOWN
Project-URL: Bug Tracker, https://github.com/MayasMess/pandas-oop/issues
Keywords: pandas,oop,dataframe,poop
Platform: UNKNOWN
Classifier: Programming Language :: Python :: 3
Classifier: License :: OSI Approved :: MIT License
Classifier: Operating System :: OS Independent
Requires-Python: >=3.6
License-File: LICENSE
Requires-Dist: pandas
Requires-Dist: pangres
Requires-Dist: sqlalchemy
